py_import_tree/__init__.py
py_import_tree/cohesion.py
py_import_tree/import_tracker.py
py_import_tree/schema.sql
py_import_tree-0.1.6.data/data/schema/schema.sql
py_import_tree-0.1.6.dist-info/LICENSE
py_import_tree-0.1.6.dist-info/METADATA
py_import_tree-0.1.6.dist-info/WHEEL
py_import_tree-0.1.6.dist-info/top_level.txt
py_import_tree-0.1.6.dist-info/RECORD
