Metadata-Version: 2.1
Name: py-import-tree
Version: 0.1.6
Summary: py_import_tree: A library for analyzing Python's code tree.
Home-page: https://github.com/hristo-vrigazov/py-import-tree
Author: Hristo Vrigazov
Author-email: hvrigazov@gmail.com
License: MIT
Platform: UNKNOWN
Classifier: License :: OSI Approved :: MIT License
Classifier: Programming Language :: Python :: 3
Classifier: Programming Language :: Python :: 3.8
Classifier: Operating System :: OS Independent
Requires-Dist: pandas
Requires-Dist: numpy
Requires-Dist: stdlib-list
Requires-Dist: astunparse
